PGUI/__init__.py
PGUI/program.py
PGUI/spacing.py
PGUI/uielement.py
PGUI/window.py
PGUI/UIElements/__init__.py
PGUI/UIElements/button.py
PGUI/UIElements/colourpicker.py
PGUI/UIElements/dropdown.py
PGUI/UIElements/editingdisplay.py
PGUI/UIElements/fpsdisplay.py
PGUI/UIElements/image.py
PGUI/UIElements/inputfield.py
PGUI/UIElements/panel.py
PGUI/UIElements/slider.py
PGUI/UIElements/text.py
PGUI/UIElements/titlescreen.py
PGUI/UIElements/togglebutton.py
PGUI/UIElements/tooltip.py
pgui_Jenson_42-0.0.2.dist-info/LICENCE
pgui_Jenson_42-0.0.2.dist-info/METADATA
pgui_Jenson_42-0.0.2.dist-info/WHEEL
pgui_Jenson_42-0.0.2.dist-info/top_level.txt
pgui_Jenson_42-0.0.2.dist-info/RECORD
